chanx/__init__.py
chanx/constants.py
chanx/py.typed
chanx/type_defs.py
chanx/asyncapi/__init__.py
chanx/asyncapi/constants.py
chanx/asyncapi/generator.py
chanx/asyncapi/type_defs.py
chanx/channels/__init__.py
chanx/channels/apps.py
chanx/channels/authenticator.py
chanx/channels/discovery.py
chanx/channels/routing.py
chanx/channels/settings.py
chanx/channels/testing.py
chanx/channels/urls.py
chanx/channels/views.py
chanx/channels/websocket.py
chanx/channels/management/__init__.py
chanx/channels/management/commands/__init__.py
chanx/channels/management/commands/generate_asyncapi_schema.py
chanx/channels/templates/channels/asyncapi_docs.html
chanx/channels/utils/__init__.py
chanx/channels/utils/asgi.py
chanx/channels/utils/request.py
chanx/channels/utils/settings.py
chanx/cli/__init__.py
chanx/cli/main.py
chanx/client_generator/__init__.py
chanx/client_generator/analyzer.py
chanx/client_generator/codegen.py
chanx/client_generator/generator.py
chanx/client_generator/loader.py
chanx/client_generator/templates.py
chanx/client_generator/base/__init__.py
chanx/client_generator/base/client.py
chanx/core/__init__.py
chanx/core/authenticator.py
chanx/core/check.py
chanx/core/config.py
chanx/core/decorators.py
chanx/core/registry.py
chanx/core/testing.py
chanx/core/websocket.py
chanx/fast_channels/__init__.py
chanx/fast_channels/constants.py
chanx/fast_channels/discovery.py
chanx/fast_channels/testing.py
chanx/fast_channels/type_defs.py
chanx/fast_channels/utils.py
chanx/fast_channels/views.py
chanx/fast_channels/websocket.py
chanx/messages/__init__.py
chanx/messages/base.py
chanx/messages/incoming.py
chanx/messages/outgoing.py
chanx/routing/__init__.py
chanx/routing/discovery.py
chanx/routing/patterns.py
chanx/routing/traversal.py
chanx/utils/__init__.py
chanx/utils/asyncio.py
chanx/utils/logging.py
chanx-2.5.0.dist-info/METADATA
chanx-2.5.0.dist-info/WHEEL
chanx-2.5.0.dist-info/entry_points.txt
chanx-2.5.0.dist-info/licenses/AUTHORS.rst
chanx-2.5.0.dist-info/licenses/LICENSE
chanx-2.5.0.dist-info/RECORD
