Metadata-Version: 2.4
Name: chanx
Version: 2.5.0
Summary: The missing toolkit for Channels — auth, logging, consumers, and more.
Project-URL: Documentation, https://chanx.readthedocs.io/
Project-URL: Homepage, https://github.com/huynguyengl99/chanx
Project-URL: Repository, https://github.com/huynguyengl99/chanx
Author-email: Huy Nguyen <danghuy1999@gmail.com>
License: 
License-File: AUTHORS.rst
License-File: LICENSE
Classifier: Environment :: Web Environment
Classifier: Intended Audience :: Developers
Classifier: Intended Audience :: Information Technology
Classifier: License :: OSI Approved :: BSD License
Classifier: Operating System :: OS Independent
Classifier: Programming Language :: Python :: 3
Classifier: Programming Language :: Python :: 3 :: Only
Classifier: Programming Language :: Python :: 3.11
Classifier: Programming Language :: Python :: 3.12
Classifier: Programming Language :: Python :: 3.13
Classifier: Topic :: Internet :: WWW/HTTP
Classifier: Topic :: Internet :: WWW/HTTP :: Dynamic Content
Classifier: Topic :: Software Development
Classifier: Topic :: Software Development :: Libraries
Classifier: Topic :: Software Development :: Libraries :: Application Frameworks
Requires-Python: <4.0,>=3.11
Requires-Dist: pydantic<3,>=2
Provides-Extra: channels
Requires-Dist: channels<5,>=4; extra == 'channels'
Requires-Dist: django>=5; extra == 'channels'
Requires-Dist: djangorestframework<4,>=3; extra == 'channels'
Requires-Dist: pyhumps>=3.8.0; extra == 'channels'
Requires-Dist: structlog; extra == 'channels'
Requires-Dist: typing-extensions; extra == 'channels'
Provides-Extra: cli
Requires-Dist: click<9,>=8.1.0; extra == 'cli'
Requires-Dist: httpx<1,>=0.27.0; extra == 'cli'
Requires-Dist: jinja2<4,>=3.1.0; extra == 'cli'
Requires-Dist: pyyaml<7,>=6.0.0; extra == 'cli'
Requires-Dist: websockets; extra == 'cli'
Provides-Extra: client
Requires-Dist: websockets; extra == 'client'
Provides-Extra: core
Requires-Dist: pyhumps>=3.8.0; extra == 'core'
Requires-Dist: structlog; extra == 'core'
Requires-Dist: typing-extensions; extra == 'core'
Provides-Extra: fast-channels
Requires-Dist: fast-channels>=1.0.2; extra == 'fast-channels'
Requires-Dist: fastapi>=0.118.0; extra == 'fast-channels'
Requires-Dist: pyhumps>=3.8.0; extra == 'fast-channels'
Requires-Dist: structlog; extra == 'fast-channels'
Requires-Dist: typing-extensions; extra == 'fast-channels'
